Hossein_Tabr/An_Wb.py
Hossein_Tabr/Cliob.py
Hossein_Tabr/Hossein_Tabr.py
Hossein_Tabr/__init__.py
Hossein_Tabr/encryption.py
Hossein_Tabr-2.0.0.dist-info/METADATA
Hossein_Tabr-2.0.0.dist-info/WHEEL
Hossein_Tabr-2.0.0.dist-info/top_level.txt
Hossein_Tabr-2.0.0.dist-info/RECORD
