Metadata-Version: 2.1
Name: Hossein-Tabr
Version: 2.0.0
Summary: Robot
Home-page: https://github.com/pypa/sampleproject
Classifier: Programming Language :: Python :: 3
Classifier: License :: OSI Approved :: MIT License
Classifier: Operating System :: OS Independent
